xuzhao_markdown/__init__.py
xuzhao_markdown/apps.py
xuzhao_markdown/forms.py
xuzhao_markdown/settings.py
xuzhao_markdown/tests.py
xuzhao_markdown/urls.py
xuzhao_markdown/utils.py
xuzhao_markdown/views.py
xuzhao_markdown/widgets.py
xuzhao_markdown/migrations/__init__.py
xuzhao_markdown/static/xuzhao_markdown/css/editormd.css
xuzhao_markdown/static/xuzhao_markdown/css/editormd.logo.css
xuzhao_markdown/static/xuzhao_markdown/css/editormd.logo.min.css
xuzhao_markdown/static/xuzhao_markdown/css/editormd.min.css
xuzhao_markdown/static/xuzhao_markdown/css/editormd.preview.css
xuzhao_markdown/static/xuzhao_markdown/css/editormd.preview.min.css
xuzhao_markdown/static/xuzhao_markdown/fonts/FontAwesome.otf
xuzhao_markdown/static/xuzhao_markdown/fonts/editormd-logo.eot
xuzhao_markdown/static/xuzhao_markdown/fonts/editormd-logo.svg
xuzhao_markdown/static/xuzhao_markdown/fonts/editormd-logo.ttf
xuzhao_markdown/static/xuzhao_markdown/fonts/editormd-logo.woff
xuzhao_markdown/static/xuzhao_markdown/fonts/fontawesome-webfont.eot
xuzhao_markdown/static/xuzhao_markdown/fonts/fontawesome-webfont.svg
xuzhao_markdown/static/xuzhao_markdown/fonts/fontawesome-webfont.ttf
xuzhao_markdown/static/xuzhao_markdown/fonts/fontawesome-webfont.woff
xuzhao_markdown/static/xuzhao_markdown/fonts/fontawesome-webfont.woff2
xuzhao_markdown/static/xuzhao_markdown/images/loading.gif
xuzhao_markdown/static/xuzhao_markdown/images/loading@2x.gif
xuzhao_markdown/static/xuzhao_markdown/images/loading@3x.gif
xuzhao_markdown/static/xuzhao_markdown/images/logos/editormd-favicon-16x16.ico
xuzhao_markdown/static/xuzhao_markdown/images/logos/editormd-favicon-24x24.ico
xuzhao_markdown/static/xuzhao_markdown/images/logos/editormd-favicon-32x32.ico
xuzhao_markdown/static/xuzhao_markdown/images/logos/editormd-favicon-48x48.ico
xuzhao_markdown/static/xuzhao_markdown/images/logos/editormd-favicon-64x64.ico
xuzhao_markdown/static/xuzhao_markdown/images/logos/editormd-logo-114x114.png
xuzhao_markdown_editor-1.1.2.dist-info/LICENSE
xuzhao_markdown_editor-1.1.2.dist-info/METADATA
xuzhao_markdown_editor-1.1.2.dist-info/WHEEL
xuzhao_markdown_editor-1.1.2.dist-info/top_level.txt
xuzhao_markdown_editor-1.1.2.dist-info/RECORD
