Metadata-Version: 2.1
Name: xuzhao-markdown-editor
Version: 1.1.2
Summary: xuzhao markdown editor
Home-page: https://github.com/twtyjvkg/xuzhao-markdown-editor
Author: xuzhao
Author-email: markdown@felinae.net
License: UNKNOWN
Keywords: django markdown editor editormd
Platform: UNKNOWN
Classifier: Programming Language :: Python
Classifier: Development Status :: 4 - Beta
Classifier: Operating System :: OS Independent
Classifier: License :: OSI Approved :: Apache Software License
Classifier: Framework :: Django
